README.txt
setup.cfg
setup.py
collective/__init__.py
collective.contentgroup.egg-info/PKG-INFO
collective.contentgroup.egg-info/SOURCES.txt
collective.contentgroup.egg-info/dependency_links.txt
collective.contentgroup.egg-info/namespace_packages.txt
collective.contentgroup.egg-info/not-zip-safe
collective.contentgroup.egg-info/requires.txt
collective.contentgroup.egg-info/top_level.txt
collective/contentgroup/README.txt
collective/contentgroup/__init__.py
collective/contentgroup/base.py
collective/contentgroup/config.py
collective/contentgroup/configure.zcml
collective/contentgroup/dynamicgroups.py
collective/contentgroup/events.py
collective/contentgroup/groupmanager.py
collective/contentgroup/interfaces.py
collective/contentgroup/browser/__init__.py
collective/contentgroup/browser/configure.zcml
collective/contentgroup/browser/fix_contentgroups.py
collective/contentgroup/tests/__init__.py
collective/contentgroup/tests/base.py
collective/contentgroup/tests/base_groupmanager.py
collective/contentgroup/tests/test_doc.py
collective/contentgroup/tests/test_dynamicgroups.py
collective/contentgroup/tests/test_group_manager.py
docs/HISTORY.txt