Metadata-Version: 1.0
Name: collective.contentgroup
Version: 0.1b3
Summary: Plone add-on that allows to associate users groups with content objects
Home-page: http://svn.plone.org/svn/collective/collective.contentgroup
Author: Rafael Oliveira
Author-email: rafaelbco@gmail.com
License: GPL
Keywords: plone groups users
Platform: UNKNOWN
Classifier: Framework :: Plone
Classifier: Programming Language :: Python
Classifier: Topic :: Software Development :: Libraries :: Python Modules
